LICENSE
MANIFEST.in
README.md
setup.py
greek_to_greeklish/__init__.py
greek_to_greeklish/greek_to_greeklish.py
greek_to_greeklish.egg-info/PKG-INFO
greek_to_greeklish.egg-info/SOURCES.txt
greek_to_greeklish.egg-info/dependency_links.txt
greek_to_greeklish.egg-info/requires.txt
greek_to_greeklish.egg-info/top_level.txt