Metadata-Version: 2.1
Name: greek-to-greeklish
Version: 0.0.8
Summary: Greek Letter Transliteration based on ELOT 743 standard
Home-page: https://github.com/timossavva/greek-to-greeklish
Author: Timotheos Savva
Author-email: 
Classifier: Programming Language :: Python :: 3
Classifier: License :: OSI Approved :: MIT License
Classifier: Operating System :: OS Independent
Requires-Python: >=3.6
License-File: LICENSE
